Workbook

Sheet COVER
B8: CAPTAIN KAP
B10: THE CREDIT CARD
B11: STRATEGY WORKBOOK
B14: Know what you have. Know what you’re missing. Know what to get next.
B17: A complete, guided system: audit your wallet, understand your credit, map your spending,
B18: pick your rewards ecosystem, build your portfolio, and plan the next 12 months — responsibly.
B21: Part of the $47 Credit Card Optimization System · captainkap.com
B23: Card data verified 2026-08 (The Points Guy 8/2/26 · Doctor of Credit 8/8/26)
B38: Educational planning tool — not financial advice. Offers, terms, and eligibility change without notice; always verify with the issuer.
B39: Rewards only have value when balances are paid in full. Never spend beyond your normal budget to earn rewards.

Sheet START HERE
A1: CAPTAIN KAP · CREDIT CARD OPTIMIZATION SYSTEM
A2: Start Here — How To Use This Workbook
A3: Work the numbered sections in order the first time through, then return to any section as your situation changes. Everything is yours to edit.
A5: THE COLOR SYSTEM
A6: Blue text = YOUR inputs — type over these.
A7: Yellow fill = the key inputs each section depends on.
A8: Black text = live calculations. Don’t type over these — they update automatically.
A9: Every fill-in table includes one EXAMPLE row in the first data row — replace it with your own.
A11: QUICK START — 20 MINUTES
A12: 1. Fill in Section 1 (Snapshot) — your income, expenses, and savings. 5 minutes.
A13: 2. List every card you own in Section 3 (Card Audit). The math lights up as you type.
A14: 3. Enter your monthly spending in Section 4 — this reveals which categories matter for YOU.
... A18: TABLE OF CONTENTS
A19: 1. SNAPSHOT | C19: Personal financial snapshot — income, expenses, debt, savings, goals
A20: 2. CREDIT PROFILE | C20: Understand your credit: utilization, age, inquiries, what to improve
A21: 3. CARD AUDIT | C21: Every card you own — limits, balances, fees, keep / downgrade / cancel
A22: 4. SPENDING | C22: Where your money actually goes, and which categories to optimize
A23: 5. REWARDS STRATEGY | C23: Cash back vs. points vs. miles — find the ecosystem that fits YOU
A24: 6. PORTFOLIO | C24: Design your card portfolio — roles, overlap check, net value
A25: 7. BONUS TRACKER | C25: Plan sign-up bonuses responsibly — pace, deadlines, progress
A26: 8. APPLICATIONS | C26: What to apply for next, when, and what to accomplish first
A27: 9. FEE ANALYSIS | C27: Is each annual fee worth it? Net value and break-even, card by card
A28: 10. WALLET STRATEGY | C28: Which card to pull out for every purchase category
A29: 11. POINTS VALUE | C29: What points are worth — cents-per-point calculator and rules of thumb
A30: 12. TRAVEL | C30: Airlines, hotels, destinations, and the points gap for upcoming trips
... A35: MY STRATEGY | C35: Your one-page consolidated strategy — the output of everything above
A37: Educational planning tool — not financial advice. Verify every offer, fee, and eligibility rule directly with the issuer.

Sheet 1. SNAPSHOT
A1: CAPTAIN KAP · CREDIT CARD OPTIMIZATION SYSTEM
A2: Section 1 · Personal Financial Snapshot
A3: Your strategy starts with reality. Fill in the blue cells — the calculations show your monthly surplus, emergency-fund coverage, and debt load. (Example values shown — replace with yours.)
A5: Item | B5: Monthly | C5: Annual | D5: Notes
A6: Gross income | B6: 6250 | C6: =IF(B6="","",B6*12) -> 75000 | D6: Before taxes and deductions
A7: Take-home income | B7: 4900 | C7: =IF(B7="","",B7*12) -> 58800 | D7: What actually hits your account
A8: Fixed expenses (rent, insurance, subscriptions…) | B8: 2300 | C8: =IF(B8="","",B8*12) -> 27600 | D8: Things that cost the same every month
A9: Variable expenses (food, gas, fun…) | B9: 1350 | C9: =IF(B9="","",B9*12) -> 16200 | D9: Estimate from the last 2–3 statements
A10: Monthly debt payments (loans, cards…) | B10: 350 | C10: =IF(B10="","",B10*12) -> 4200 | D10: Minimums + planned extra payments
A11: Monthly surplus (take-home − expenses − debt) | B11: =IF(B7="","",B7-B8-B9-B10) -> 900 | C11: =IF(B11="","",B11*12) -> 10800 | D11: Negative? Fix this before any rewards strategy — rewards never beat interest.
A13: Balances & profile | B13: Amount | D13: Notes
A14: Total savings | B14: 9500 | D14: Checking + savings you could actually use
A15: Emergency fund (part of savings) | B15: 6000 | D15: Money you will NOT touch for rewards or travel
A16: Total non-mortgage debt | B16: 4200 | D16: Cards, auto, personal, student
A17: Credit score (approximate) | B17: 735 | D17: From your bank or a free monitoring service
A18: Number of credit cards you have | B18: 3 | D18: Count every open card
A19: Annual fees you currently pay (total) | B19: 420 | D19: Section 9 computes this precisely
A20: Current points / miles balances (est. value $) | B20: 300 | D20: Rough guess now; Section 11 sharpens it
A21: Emergency fund coverage (months of essentials) | B21: =IF(OR(B15="",B8=""),"",ROUND(B15/MAX(1,B8),1)) -> 2.6 | D21: 3–6 months is the widely-cited planning range. Below 3? Build this before chasing bonuses.
A22: Debt-to-income (monthly debt ÷ take-home) | B22: =IF(OR(B10="",B7=""),"",B10/MAX(1,B7)) -> 0.071428571 | D22: Lower is better; lenders look at this when you apply.
A24: MY FINANCIAL GOALS (write freely)
A25: This year I want to…
A26: In 3 years I want to…
A27: Rewards will help me…

Sheet 2. CREDIT PROFILE
A1: CAPTAIN KAP · CREDIT CARD OPTIMIZATION SYSTEM
A2: Section 2 · Credit Profile Assessment
A3: Card strategy is built ON good credit, never at its expense. Fill in what you know — free monitoring tools from your bank cover most of this.
A5: Factor | B5: Yours | C5: What it means & how to improve it
A6: Credit score | B6: 735 | C6: Payment history and utilization drive most of your score. 670+ is commonly cited as "good," 740+ "very good" — check your own lender’s tiers.
A7: Overall utilization (all balances ÷ all limits) | B7: =IF('3. CARD AUDIT'!C18=0,"",'3. CARD AUDIT'!D18/'3. CARD AUDIT'!C18) -> 0.085 | C7: Auto-calculated from Section 3. Keeping utilization under ~30% — ideally under 10% — is one of the most-cited score levers.
A8: Number of open accounts | B8: 3 | C8: More accounts = more available credit and lower utilization, but only open cards you’d keep anyway.
A9: Average age of accounts (years) | B9: 3.5 | C9: Older is better. This is why "cancel it" is rarely the first move — downgrading keeps the age.
A10: Oldest account (years) | B10: 6 | C10: Protect this card. Even unused, it anchors your history — consider a no-fee downgrade instead of canceling.
A11: Hard inquiries — last 12 months | B11: 1 | C11: Each application typically adds one. Several in a short window can look risky to issuers and trips rules like Chase 5/24.
A12: Cards opened — last 24 months | B12: 1 | C12: Chase’s widely-reported 5/24 rule: 5+ new personal cards in 24 months usually means automatic denial at Chase.
A13: Late payments — last 24 months | B13: 0 | C13: The single most damaging item. Autopay at least the minimum on every card, forever.
A14: Total credit limits | B14: =IF('3. CARD AUDIT'!C18=0,"",'3. CARD AUDIT'!C18) -> 10000 | C14: Auto from Section 3.
A15: Total balances | B15: =IF('3. CARD AUDIT'!C18=0,"",'3. CARD AUDIT'!D18) -> 850 | C15: Auto from Section 3. If this isn’t paid in full monthly, stop here: interest erases rewards many times over.
A17: IMPROVEMENT CHECKLIST — mark what applies
A18: Set autopay (at least minimum) on every card
A19: Pay balances in full every month
A20: Keep overall utilization under 30% (aim <10%)
A21: Keep the oldest card open (downgrade, don’t cancel)
A22: Space applications out — no bursts of inquiries
A23: Check reports for errors at annualcreditreport.com

Sheet 3. CARD AUDIT
A1: CAPTAIN KAP · CREDIT CARD OPTIMIZATION SYSTEM
A2: Section 3 · Current Card Audit
A3: List EVERY card you have. Pick from the dropdown (the Card Database auto-fills issuer + typical fee) or type any card. Row 6 is an example — overwrite it.
A5: Card | B5: Issuer (auto if in DB) | C5: Credit limit | D5: Balance | E5: APR % | F5: Annual fee | G5: Opened (YYYY-MM) | H5: Utilization | I5: Rewards currency | J5: Earn rates | K5: Sign-up bonus you got / spend req / deadline | L5: Authorized users? | M5: Verdict | N5: Benefits, credits & notes
A6: American Express Gold | B6: =IF(A6="","",IFERROR(INDEX('CARD DATABASE'!$B$5:$B$34,MATCH(A6,'CARD DATABASE'!$A$5:$A$34,0)),"—")) -> Amex | C6: 10000 | D6: 850 | E6: 29.24 | F6: 325 | G6: 2024-03 | H6: =IF(OR(C6="",C6=0),"",D6/C6) -> 0.085 | I6: Amex MR | J6: 4x dining · 4x U.S. supermarkets | K6: 60K MR / $6K in 6mo / met | L6: No | M6: Keep | N6: $120 Uber Cash + $120 dining credits — using both
B7: =IF(A7="","",IFERROR(INDEX('CARD DATABASE'!$B$5:$B$34,MATCH(A7,'CARD DATABASE'!$A$5:$A$34,0)),"—")) | H7: =IF(OR(C7="",C7=0),"",D7/C7)
B8: =IF(A8="","",IFERROR(INDEX('CARD DATABASE'!$B$5:$B$34,MATCH(A8,'CARD DATABASE'!$A$5:$A$34,0)),"—")) | H8: =IF(OR(C8="",C8=0),"",D8/C8)
B9: =IF(A9="","",IFERROR(INDEX('CARD DATABASE'!$B$5:$B$34,MATCH(A9,'CARD DATABASE'!$A$5:$A$34,0)),"—")) | H9: =IF(OR(C9="",C9=0),"",D9/C9)
B10: =IF(A10="","",IFERROR(INDEX('CARD DATABASE'!$B$5:$B$34,MATCH(A10,'CARD DATABASE'!$A$5:$A$34,0)),"—")) | H10: =IF(OR(C10="",C10=0),"",D10/C10)
B11: =IF(A11="","",IFERROR(INDEX('CARD DATABASE'!$B$5:$B$34,MATCH(A11,'CARD DATABASE'!$A$5:$A$34,0)),"—")) | H11: =IF(OR(C11="",C11=0),"",D11/C11)
B12: =IF(A12="","",IFERROR(INDEX('CARD DATABASE'!$B$5:$B$34,MATCH(A12,'CARD DATABASE'!$A$5:$A$34,0)),"—")) | H12: =IF(OR(C12="",C12=0),"",D12/C12)
B13: =IF(A13="","",IFERROR(INDEX('CARD DATABASE'!$B$5:$B$34,MATCH(A13,'CARD DATABASE'!$A$5:$A$34,0)),"—")) | H13: =IF(OR(C13="",C13=0),"",D13/C13)
B14: =IF(A14="","",IFERROR(INDEX('CARD DATABASE'!$B$5:$B$34,MATCH(A14,'CARD DATABASE'!$A$5:$A$34,0)),"—")) | H14: =IF(OR(C14="",C14=0),"",D14/C14)
B15: =IF(A15="","",IFERROR(INDEX('CARD DATABASE'!$B$5:$B$34,MATCH(A15,'CARD DATABASE'!$A$5:$A$34,0)),"—")) | H15: =IF(OR(C15="",C15=0),"",D15/C15)
B16: =IF(A16="","",IFERROR(INDEX('CARD DATABASE'!$B$5:$B$34,MATCH(A16,'CARD DATABASE'!$A$5:$A$34,0)),"—")) | H16: =IF(OR(C16="",C16=0),"",D16/C16)
B17: =IF(A17="","",IFERROR(INDEX('CARD DATABASE'!$B$5:$B$34,MATCH(A17,'CARD DATABASE'!$A$5:$A$34,0)),"—")) | H17: =IF(OR(C17="",C17=0),"",D17/C17)
A18: TOTALS | C18: =SUM(C6:C17) -> 10000 | D18: =SUM(D6:D17) -> 850 | F18: =SUM(F6:F17) -> 325 | H18: =IF(C18=0,"",D18/C18) -> 0.085
A20: Verdict guide — KEEP: you use it and it earns its fee (Section 9 proves it). DOWNGRADE: fee card you don’t use → ask the issuer for a no-fee version, keeping the account age. CANCEL: last resort — usually only for high fees with no downgrade path. Utilization and account age both matter to your score (Section 2).

Sheet 4. SPENDING
A1: CAPTAIN KAP · CREDIT CARD OPTIMIZATION SYSTEM
A2: Section 4 · Spending Analysis
A3: Where does your money actually go? Pull 2–3 months of statements and average them. The % column shows which categories matter enough to optimize.
A5: Category | B5: Monthly | C5: Annual | D5: % of total | E5: Best card you own for this | F5: Optimization notes (which cards excel here)
A6: Groceries | B6: 650 | C6: =IF(B6="","",B6*12) -> 7800 | D6: =IF(OR(B6="",B$19=0),"",B6/B$19) -> 0.15169195 | E6: Amex Gold | F6: Category kings: Amex Gold (4x U.S. supermarkets), Citi Strata (3x)
A7: Dining & restaurants | B7: 420 | C7: =IF(B7="","",B7*12) -> 5040 | D7: =IF(OR(B7="",B$19=0),"",B7/B$19) -> 0.098016336 | F7: Amex Gold (4x), Sapphire Preferred (3x), Savor (3%)
A8: Gas | B8: 180 | C8: =IF(B8="","",B8*12) -> 2160 | D8: =IF(OR(B8="",B$19=0),"",B8/B$19) -> 0.042007001 | F8: Citi Strata (3x); many co-brands add gas
A9: Travel — flights | B9: 150 | C9: =IF(B9="","",B9*12) -> 1800 | D9: =IF(OR(B9="",B$19=0),"",B9/B$19) -> 0.035005834 | F9: Amex Platinum (5x flights), Sapphire Reserve, airline cards
A10: Travel — hotels | B10: 120 | C10: =IF(B10="","",B10*12) -> 1440 | D10: =IF(OR(B10="",B$19=0),"",B10/B$19) -> 0.028004667 | F10: Autograph Journey (5x), portals, hotel co-brands
A11: Online shopping | B11: 260 | C11: =IF(B11="","",B11*12) -> 3120 | D11: =IF(OR(B11="",B$19=0),"",B11/B$19) -> 0.060676779 | F11: Often 1x territory — a 2% flat card usually wins
A12: Utilities & phone | B12: 280 | C12: =IF(B12="","",B12*12) -> 3360 | D12: =IF(OR(B12="",B$19=0),"",B12/B$19) -> 0.065344224 | F12: Rarely bonused — flat-rate card
A13: Streaming & subscriptions | B13: 65 | C13: =IF(B13="","",B13*12) -> 780 | D13: =IF(OR(B13="",B$19=0),"",B13/B$19) -> 0.015169195 | F13: Small but steady — some cards credit these
A14: Entertainment | B14: 110 | C14: =IF(B14="","",B14*12) -> 1320 | D14: =IF(OR(B14="",B$19=0),"",B14/B$19) -> 0.025670945 | F14: Savor (3% entertainment)
A15: Insurance | B15: 210 | C15: =IF(B15="","",B15*12) -> 2520 | D15: =IF(OR(B15="",B$19=0),"",B15/B$19) -> 0.049008168 | F15: Flat-rate card; check for processing fees
A16: Rent / mortgage | B16: 1600 | C16: =IF(B16="","",B16*12) -> 19200 | D16: =IF(OR(B16="",B$19=0),"",B16/B$19) -> 0.37339557 | F16: Usually can’t pay by card without fees — only worth it for a bonus you’d hit anyway, never for regular points
A17: Business expenses | B17: 0 | C17: =IF(B17="","",B17*12) -> 0 | D17: =IF(OR(B17="",B$19=0),"",B17/B$19) -> 0 | F17: Business cards keep this separate (Ink, Amex Business)
A18: Everything else | B18: 240 | C18: =IF(B18="","",B18*12) -> 2880 | D18: =IF(OR(B18="",B$19=0),"",B18/B$19) -> 0.056009335 | F18: Your flat-rate 1.5–2% anchor
A19: TOTAL | B19: =SUM(B6:B18) -> 4285 | C19: =SUM(C6:C18) -> 51420
A21: Your top-3 categories (by %): | B21: Optimize these FIRST — a bonus category you barely use is worth nothing.
A22: #1
A23: #2
A24: #3

Sheet 5. REWARDS STRATEGY
A1: CAPTAIN KAP · CREDIT CARD OPTIMIZATION SYSTEM
A2: Section 5 · Rewards Strategy — Which Ecosystem Fits YOU?
A3: There is no "best" system — there is a best system for YOUR spending and travel. Read the four paths, take the quiz, then commit to one primary direction.
A5: CASH BACK | B5: Simple, flexible, zero learning curve. 1.5–2% on everything, more in categories. Best if you value simplicity, don’t travel much, or want guaranteed value.
A6: TRANSFERABLE POINTS (Chase UR · Amex MR · Citi TY · Capital One) | B6: The power-user path: points move to airline/hotel partners where redemptions can beat 2¢/pt — or fall back to ~1¢ cash-style floors. Best if you travel and enjoy optimizing.
A7: AIRLINE MILES | B7: Earn into one airline you actually fly. Bags, boarding, and awards — but miles devalue and lock you in. Best as a complement, rarely as the core.
A8: HOTEL POINTS | B8: Free nights and status with one chain (5th-night-free at Hilton & Marriott stretches them). Same trade-off: loyalty for flexibility.
A10: THE 5-QUESTION QUIZ — answer Yes/No
A11: Do you take 2+ leisure trips a year (or want to)? | C11: Travel unlocks the outsized value of points.
A12: Do you pay every card in full, every month, without thinking? | C12: If not, the answer is cash back — or no rewards at all until you do.
A13: Are you willing to spend ~1 hour/month managing cards & points? | C13: Optimization has a real time cost.
A14: Is your top spending in bonus-able categories (Section 4: dining/groceries/travel)? | C14: Category multipliers need matching spend.
A15: Would you enjoy booking a business-class seat with points? | C15: The single biggest win transferable points offer.
A16: "Yes" count | B16: =IF(COUNTBLANK(B11:B15)>0,"",COUNTIF(B11:B15,"Yes"))
A17: Suggested direction | B17: =IF(B16="","— answer all 5 —",IF(B16>=4,"Transferable points",IF(B16>=2,"Hybrid: cash back + one points card","Cash back"))) -> — answer all 5 —
A18: A guideline, not a rule — question 2 is the veto: never carry a balance for points.
A20: EFFECTIVE REWARDS RATE — what are you ACTUALLY earning?
A21: Rewards earned last 12 months (cash value, $) | B21: 380
A22: Card spending last 12 months ($) | B22: 28000
A23: Effective rate | B23: =IF(OR(B21="",B22="",B22=0),"",B21/B22) -> 0.013571429 | C23: Under 1.5%? A single 2% flat card would beat your current setup. Over 3%? You’re optimizing well.
A25: Opportunity cost & simplicity: every card you add costs attention — fees to track, credits to remember, categories to think about. The right portfolio is the SIMPLEST one that captures your top categories (Section 4), not the biggest one.

Sheet 6. PORTFOLIO
A1: CAPTAIN KAP · CREDIT CARD OPTIMIZATION SYSTEM
A2: Section 6 · Portfolio Builder
A3: Design your wallet on paper before you apply for anything. Each card needs ONE clear role — two cards with the same role is a fee you don’t need.
A5: Card | B5: Status | C5: Role in portfolio | D5: Annual fee | E5: Expected rewards / yr ($) | F5: Benefits value / yr ($) | G5: Net value / yr | H5: Sign-up bonus & spend req | I5: Credit limit | J5: Purpose — why THIS card
A6: American Express Gold | B6: Own | C6: Dining & groceries | D6: 325 | E6: 520 | F6: 240 | G6: =IF(AND(E6="",F6=""),"",SUM(E6,F6)-IF(D6="",0,D6)) -> 435 | H6: 60K MR — met | I6: 10000 | J6: Food is my #1 category (Sec 4) — 4x turns it into the points engine
G7: =IF(AND(E7="",F7=""),"",SUM(E7,F7)-IF(D7="",0,D7))
G8: =IF(AND(E8="",F8=""),"",SUM(E8,F8)-IF(D8="",0,D8))
G9: =IF(AND(E9="",F9=""),"",SUM(E9,F9)-IF(D9="",0,D9))
G10: =IF(AND(E10="",F10=""),"",SUM(E10,F10)-IF(D10="",0,D10))
G11: =IF(AND(E11="",F11=""),"",SUM(E11,F11)-IF(D11="",0,D11))
G12: =IF(AND(E12="",F12=""),"",SUM(E12,F12)-IF(D12="",0,D12))
G13: =IF(AND(E13="",F13=""),"",SUM(E13,F13)-IF(D13="",0,D13))
G14: =IF(AND(E14="",F14=""),"",SUM(E14,F14)-IF(D14="",0,D14))
G15: =IF(AND(E15="",F15=""),"",SUM(E15,F15)-IF(D15="",0,D15))
A16: PORTFOLIO TOTALS | D16: =SUM(D6:D15) -> 325 | E16: =SUM(E6:E15) -> 520 | F16: =SUM(F6:F15) -> 240 | G16: =SUM(G6:G15) -> 435
A18: OVERLAP CHECK: scan the Role column — any role appearing twice needs a reason (e.g., a business + personal pair). Estimate "expected rewards" honestly from Section 4 spending × the card’s earn rate, and count only benefits you would use anyway. Net value = rewards + benefits − fee.

Sheet 7. BONUS TRACKER
A1: CAPTAIN KAP · CREDIT CARD OPTIMIZATION SYSTEM
A2: Section 7 · Sign-Up Bonus Tracker
A3: Plan every bonus around spending you already do. If a required spend is above your normal budget, the answer is a smaller bonus — not bigger spending.
A5: ⚠ NEVER manufacture spending, overspend, or carry a balance to earn a bonus. Interest and impulse purchases erase bonus value instantly. Bonuses are earned with planned, normal spending — or not at all.
A7: Card | B7: Bonus offered | C7: Min spend | D7: Deadline (date) | E7: Spent so far | F7: Remaining | G7: Days left | H7: Required $/mo pace | I7: My planned $/mo | J7: Est. bonus value ($) | K7: Planned purchases that get me there
A8: American Express Gold | B8: 60,000 MR | C8: 6000 | D8: 46402 | E8: 2100 | F8: =IF(C8="","",MAX(0,C8-IF(E8="",0,E8))) -> 3900 | G8: =IF(D8="","",MAX(0,D8-TODAY())) -> 157 | H8: =IF(OR(C8="",D8="",D8-TODAY()<=0),"",ROUND(F8/MAX(1,(D8-TODAY())/30.4),0)) -> 755 | I8: 700 | J8: 600 | K8: Groceries, insurance renewal, planned tire replacement
F9: =IF(C9="","",MAX(0,C9-IF(E9="",0,E9))) | G9: =IF(D9="","",MAX(0,D9-TODAY())) | H9: =IF(OR(C9="",D9="",D9-TODAY()<=0),"",ROUND(F9/MAX(1,(D9-TODAY())/30.4),0))
F10: =IF(C10="","",MAX(0,C10-IF(E10="",0,E10))) | G10: =IF(D10="","",MAX(0,D10-TODAY())) | H10: =IF(OR(C10="",D10="",D10-TODAY()<=0),"",ROUND(F10/MAX(1,(D10-TODAY())/30.4),0))
F11: =IF(C11="","",MAX(0,C11-IF(E11="",0,E11))) | G11: =IF(D11="","",MAX(0,D11-TODAY())) | H11: =IF(OR(C11="",D11="",D11-TODAY()<=0),"",ROUND(F11/MAX(1,(D11-TODAY())/30.4),0))
F12: =IF(C12="","",MAX(0,C12-IF(E12="",0,E12))) | G12: =IF(D12="","",MAX(0,D12-TODAY())) | H12: =IF(OR(C12="",D12="",D12-TODAY()<=0),"",ROUND(F12/MAX(1,(D12-TODAY())/30.4),0))
F13: =IF(C13="","",MAX(0,C13-IF(E13="",0,E13))) | G13: =IF(D13="","",MAX(0,D13-TODAY())) | H13: =IF(OR(C13="",D13="",D13-TODAY()<=0),"",ROUND(F13/MAX(1,(D13-TODAY())/30.4),0))
A15: Pace check | B15: =IF(OR(H8="",I8=""),"",IF(I8>=H8,"On track at your planned pace","Behind — required pace exceeds your plan. Choose: adjust timing, or let it go.")) -> Behind — required pace exceeds your plan. Choose: adjust timing, or let it go.
A17: Estimated bonus value: points × a conservative value (Section 11). Weigh it against the fee AND your time. A bonus you have to strain for is a bonus that costs more than it pays.

Sheet 8. APPLICATIONS
A1: CAPTAIN KAP · CREDIT CARD OPTIMIZATION SYSTEM
A2: Section 8 · Application Strategy
A3: What next, why, and when. Approval is NEVER guaranteed — this framework maximizes your odds and protects your credit while you build.
A5: READINESS CHECK — answer Yes/No
A6: Utilization under 30% right now? | B6: Yes | C6: High utilization is the most common denial reason issuers cite.
A7: Fewer than 3 hard inquiries in the last 6 months? | C7: Bursts of applications read as risk.
A8: Under 5 new personal cards in 24 months? | C8: Chase’s widely-reported 5/24 threshold — verify current policy.
A9: Emergency fund at 3+ months (Section 1)? | C9: Never build a card portfolio on a fragile foundation.
A10: Can you meet the target card’s minimum spend with NORMAL spending? | C10: If no, this isn’t your next card — whatever the bonus.
A11: Readiness signal | B11: =IF(COUNTBLANK(B6:B10)>0,"",IF(COUNTIF(B6:B10,"Yes")=5,"Green — positioned well",IF(COUNTIF(B6:B10,"Yes")>=3,"Yellow — fix the No answers first","Red — build first, apply later")))
A13: MY NEXT-CARD SHORTLIST
A14: Candidate card | B14: Target offer / source | C14: Why this card — and what I must accomplish first
A15: Chase Sapphire Preferred | B15: Check current offer — verify with issuer | C15: Unlocks UR transfers for my Hyatt goal (Sec 12). First: finish Amex Gold bonus, drop utilization below 10%.
A19: THE RULES OF APPLICATION VELOCITY
A20: • Space applications ~3+ months apart as a default — slower if scores dip.
A21: • Know issuer patterns before you apply (commonly reported — verify): Chase 5/24 · Amex once-per-lifetime bonus language · Capital One sensitivity to many recent accounts.
A22: • An existing relationship (deposits, older cards) can help — apply where you already bank when it’s close.
A23: • Timing matters: apply when a strong offer aligns with planned spending (a move, insurance renewals) — never create spending to justify a card.
A24: • Denied? Don’t reflex-reapply. Call the reconsideration line, understand the reason, fix it.

Sheet 9. FEE ANALYSIS
A1: CAPTAIN KAP · CREDIT CARD OPTIMIZATION SYSTEM
A2: Section 9 · Annual Fee Analysis
A3: A fee is a subscription — worth it only if you would buy what it includes anyway. Count ONLY credits and benefits you genuinely use.
A5: Card | B5: Annual fee | C5: Credits I actually use ($/yr) | D5: Benefits value I use ($/yr) | E5: Rewards earned ($/yr) | F5: Net value (value − fee) | G5: Verdict | H5: Break-even & notes
A6: American Express Gold | B6: 325 | C6: 240 | D6: 80 | E6: 520 | F6: =IF(B6="","",SUM(C6:E6)-B6) -> 515 | G6: =IF(B6="","",IF(SUM(C6:E6)-B6>=0,"KEEP","REVIEW")) -> KEEP | H6: Break-even: fee is covered by credits alone if I use Uber + dining every month
F7: =IF(B7="","",SUM(C7:E7)-B7) | G7: =IF(B7="","",IF(SUM(C7:E7)-B7>=0,"KEEP","REVIEW"))
F8: =IF(B8="","",SUM(C8:E8)-B8) | G8: =IF(B8="","",IF(SUM(C8:E8)-B8>=0,"KEEP","REVIEW"))
F9: =IF(B9="","",SUM(C9:E9)-B9) | G9: =IF(B9="","",IF(SUM(C9:E9)-B9>=0,"KEEP","REVIEW"))
F10: =IF(B10="","",SUM(C10:E10)-B10) | G10: =IF(B10="","",IF(SUM(C10:E10)-B10>=0,"KEEP","REVIEW"))
F11: =IF(B11="","",SUM(C11:E11)-B11) | G11: =IF(B11="","",IF(SUM(C11:E11)-B11>=0,"KEEP","REVIEW"))
F12: =IF(B12="","",SUM(C12:E12)-B12) | G12: =IF(B12="","",IF(SUM(C12:E12)-B12>=0,"KEEP","REVIEW"))
F13: =IF(B13="","",SUM(C13:E13)-B13) | G13: =IF(B13="","",IF(SUM(C13:E13)-B13>=0,"KEEP","REVIEW"))
F14: =IF(B14="","",SUM(C14:E14)-B14) | G14: =IF(B14="","",IF(SUM(C14:E14)-B14>=0,"KEEP","REVIEW"))
F15: =IF(B15="","",SUM(C15:E15)-B15) | G15: =IF(B15="","",IF(SUM(C15:E15)-B15>=0,"KEEP","REVIEW"))
A16: TOTALS | B16: =SUM(B6:B15) -> 325 | C16: =SUM(C6:C15) -> 240 | D16: =SUM(D6:D15) -> 80 | E16: =SUM(E6:E15) -> 520 | F16: =SUM(F6:F15) -> 515
A18: REVIEW ≠ cancel. First ask for a retention offer, then check the no-fee downgrade path (keeps your account age — Section 2), and only then consider canceling. Military note: SCRA/MLA fee waivers are typical for eligible active duty at several issuers — verify your eligibility directly.

Sheet 10. WALLET STRATEGY
A1: CAPTAIN KAP · CREDIT CARD OPTIMIZATION SYSTEM
A2: Section 10 · Wallet Strategy — Which Card For Which Purchase
A3: The output of everything so far: a one-glance answer to "which card do I pull out?" Fill it, then screenshot it for your phone.
A5: Purchase category | B5: Card I use | C5: Earn rate | D5: Why / reminders
A6: Dining | B6: American Express Gold | C6: 4x MR | D6: Includes takeout & delivery — check terms
A7: Groceries | B7: American Express Gold | C7: 4x MR | D7: U.S. supermarkets; warehouse clubs usually excluded
A8: Gas
A9: Flights
A10: Hotels
A11: Online shopping
A12: Streaming
A13: Everyday / everything else
A14: Big one-off purchases | D14: Route to an active bonus (Section 7) if one is in progress
A15: Rotating category — this quarter | D15: Update quarterly (Freedom Flex-style cards)
A17: ROTATING CATEGORIES — QUARTER PLANNER
A18: Quarter | B18: Category | C18: Card | D18: Activated?
A19: Q1
A20: Q2
A21: Q3
A22: Q4
A24: One active-bonus override: while a sign-up bonus is in progress, planned spending goes THERE first, categories second.

Sheet 11. POINTS VALUE
A1: CAPTAIN KAP · CREDIT CARD OPTIMIZATION SYSTEM
A2: Section 11 · Points & Miles Valuation
A3: A point has no fixed worth — it’s worth what YOUR redemption gets. This page turns any redemption into cents-per-point so you can compare apples to apples.
A5: THE FORMULA
A6: Value per point (¢) = (cash price − award taxes/fees) ÷ points required × 100
A8: CENTS-PER-POINT CALCULATOR
A9: Redemption I’m considering | B9: Cash price ($) | C9: Award taxes/fees ($) | D9: Points required | E9: ¢ per point | F9: Read | G9: Notes
A10: Round-trip economy to London on points | B10: 780 | C10: 180 | D10: 30000 | E10: =IF(OR(B10="",D10="",D10=0),"",ROUND((B10-IF(C10="",0,C10))/D10*100,2)) -> 2 | F10: =IF(E10="","",IF(E10<1,"Weak — cash likely better",IF(E10<1.5,"Okay",IF(E10<2.5,"Good","Excellent")))) -> Good | G10: Example — replace with your real quotes
E11: =IF(OR(B11="",D11="",D11=0),"",ROUND((B11-IF(C11="",0,C11))/D11*100,2)) | F11: =IF(E11="","",IF(E11<1,"Weak — cash likely better",IF(E11<1.5,"Okay",IF(E11<2.5,"Good","Excellent"))))
E12: =IF(OR(B12="",D12="",D12=0),"",ROUND((B12-IF(C12="",0,C12))/D12*100,2)) | F12: =IF(E12="","",IF(E12<1,"Weak — cash likely better",IF(E12<1.5,"Okay",IF(E12<2.5,"Good","Excellent"))))
E13: =IF(OR(B13="",D13="",D13=0),"",ROUND((B13-IF(C13="",0,C13))/D13*100,2)) | F13: =IF(E13="","",IF(E13<1,"Weak — cash likely better",IF(E13<1.5,"Okay",IF(E13<2.5,"Good","Excellent"))))
E14: =IF(OR(B14="",D14="",D14=0),"",ROUND((B14-IF(C14="",0,C14))/D14*100,2)) | F14: =IF(E14="","",IF(E14<1,"Weak — cash likely better",IF(E14<1.5,"Okay",IF(E14<2.5,"Good","Excellent"))))
E15: =IF(OR(B15="",D15="",D15=0),"",ROUND((B15-IF(C15="",0,C15))/D15*100,2)) | F15: =IF(E15="","",IF(E15<1,"Weak — cash likely better",IF(E15<1.5,"Okay",IF(E15<2.5,"Good","Excellent"))))
A17: Thresholds are general guidelines, not rules — YOUR alternative always matters most.
A19: WHEN TO CASH OUT vs. TRANSFER
A20: • Cash out (portal / statement credit) when: the CPP math lands near your cash floor (~1¢), you need flexibility, or you don’t have a specific award.
A21: • Transfer to a partner when: you have FOUND a specific bookable award whose CPP clearly beats the floor — transfers are one-way and final.
A22: • Never transfer speculatively. Find the seat or room first, confirm it books, then move exactly the points you need.
A23: • Valuations vary by program and change with devaluations — treat every published "point value" as an estimate, and run your own math above.

Sheet 12. TRAVEL
A1: CAPTAIN KAP · CREDIT CARD OPTIMIZATION SYSTEM
A2: Section 12 · Travel Strategy
A3: Point strategies only work aimed at real trips. Anchor yours to how you actually travel — then plan the points for each specific trip.
A5: My travel profile | B5: Answer | E5: Notes
A6: Home airport(s) | B6: DEN
A7: Airlines I fly most | B7: United, Southwest
A8: Airline status (if any)
A9: Hotel brands I prefer | B9: Hyatt
A10: Hotel status (if any)
A11: Trips per year (typical) | B11: 3
A12: Common destinations | B12: Family in TX; Europe someday
A13: Travel style | B13: Economy now, one big trip/yr
A15: MY POINTS BALANCES
A16: Program | B16: Points now | C16: Est. value ¢/pt (your guess) | D16: Est. value ($) | E16: Notes
A17: Amex Membership Rewards | B17: 62000 | C17: 1.5 | D17: =IF(OR(B17="",C17=""),"",B17*C17/100) -> 930
D18: =IF(OR(B18="",C18=""),"",B18*C18/100)
D19: =IF(OR(B19="",C19=""),"",B19*C19/100)
D20: =IF(OR(B20="",C20=""),"",B20*C20/100)
D21: =IF(OR(B21="",C21=""),"",B21*C21/100)
A23: UPCOMING TRIPS — THE POINTS GAP
A24: Trip | B24: When | C24: Program I’d book with | D24: Points needed | E24: Points I have | F24: Points gap | G24: Plan to close the gap
A25: Spring trip to see family | B25: 2027-04 | C25: Southwest Rapid Rewards | D25: 25000 | E25: 11000 | F25: =IF(D25="","",MAX(0,D25-IF(E25="",0,E25))) -> 14000 | G25: Transfer UR after CSP bonus posts
F26: =IF(D26="","",MAX(0,D26-IF(E26="",0,E26)))
F27: =IF(D27="","",MAX(0,D27-IF(E27="",0,E27)))
F28: =IF(D28="","",MAX(0,D28-IF(E28="",0,E28)))
A30: Transfer partners: your transferable points (Section 5) reach these programs — the site’s Points Strategy tab lists current partners, ratios, and verified transfer bonuses. Always confirm award space BEFORE transferring.

Sheet 13. 12-MONTH PLAN
A1: CAPTAIN KAP · CREDIT CARD OPTIMIZATION SYSTEM
A2: Section 13 · 12-Month Strategy Planner
A3: Strategy is a calendar, not a wish. One line per month — small objectives, reviewed monthly, compound into a completely different position by month 12.
A5: Month | B5: Financial objective | C5: Credit objective | D5: Card / bonus objective | E5: Spending objective | F5: Points objective | G5: Review date | H5: Notes
A6: Month 1 | B6: Refill emergency fund to 3 months | C6: Set autopay on all cards | D6: Finish Amex Gold bonus ($900 to go) | E6: Keep dining on Gold | F6: Value MR balance (Sec 11) | G6: 2026-09-01
A7: Month 2
A8: Month 3
A9: Month 4
A10: Month 5
A11: Month 6
A12: Month 7
A13: Month 8
A14: Month 9
A15: Month 10
A16: Month 11
A17: Month 12
A19: Monthly review ritual (15 min): check bonus pace (Sec 7) · check utilization (Sec 3) · claim monthly credits · update this row · set next review date.

Sheet 14. LONG-TERM
A1: CAPTAIN KAP · CREDIT CARD OPTIMIZATION SYSTEM
A2: Section 14 · Long-Term Strategy
A3: Zoom out. Cards are a tool for a bigger financial life — name where you’re going so every application serves it.
A5: Horizon | B5: Credit & cards | C5: Rewards & travel | D5: Money & major purchases
A6: 1 year | B6: Score 750+, utilization <10% | C6: First business-class-worthy balance | D6: 6-month emergency fund
A7: 2 years
A8: 3 years
A10: Major upcoming purchases (next 3 years) | B10: Approx. when | C10: Approx. amount | D10: How cards fit (bonus timing? 0% offer? NONE?)
A11: New tires + brakes | B11: 2026-11 | C11: 900 | D11: Times perfectly against CSP minimum spend — already planned
A16: A major purchase you were ALREADY making is the best bonus fuel there is. A purchase invented to feed a bonus is the most expensive mistake in this hobby.

Sheet RULES & SAFETY
A1: READ THIS FIRST · READ IT AGAIN LATER
A2: The Rules — Responsible Credit, Non-Negotiable
A3: Everything in this workbook works ONLY on this foundation. Read, agree, and hold the line.
A5: The rule | B5: I agree | C5: Why it matters
A6: Never spend money solely to earn rewards. | C6: Rewards return 1–5%. Spending $100 to earn $2 is losing $98.
A7: Never carry a balance to earn points. | C7: Interest at 20%+ APR erases a year of rewards in weeks.
A8: Pay every statement on time — autopay the minimum as a floor. | C8: Payment history is the biggest score factor, and late fees compound.
A9: Know every card’s APR — and behave as if you’ll never pay it. | C9: The APR only matters if you break rule #2. Don’t.
A10: Know every annual fee and what it buys (Section 9). | C10: Fees are fine when they’re net-positive. Unexamined fees are a leak.
A11: Never apply for a card only because the bonus is shiny. | C11: The card must have a role in YOUR portfolio (Section 6) — bonus second.
A12: If rewards make you spend more, stop chasing rewards. | C12: The psychology is real. Track it honestly in Section 4.
A13: Keep your emergency fund funded before optimizing anything. | C13: 3–6 months of essentials (Section 1). Cards are not an emergency fund.
A14: Approval is never guaranteed — plan for a “no.” | C14: Issuers weigh factors you can’t see. A denial is information, not failure.
A15: Verify EVERYTHING with the issuer before applying. | C15: Offers, fees, eligibility rules, and benefits change without notice.
A16: Rules acknowledged | B16: =COUNTIF(B6:B15,"I agree")&" / 10" -> 0 / 10

Sheet CARD DATABASE
A1: Card Database — Current vs. Typical Offers
A2: Verified 2026-08 · Sources: The Points Guy (8/2/26), Doctor of Credit (8/8/26) · Offers vary by applicant and change without notice — ALWAYS verify the live offer and military (SCRA/MLA) fee policy with the issuer before applying.
A4: Card | B4: Issuer | C4: Type | D4: Annual Fee | E4: Current Offer | F4: Typical Offer | G4: Verified | H4: Source | I4: Earning | J4: Purpose | K4: Military / Eligibility Notes
A5: Chase Sapphire Preferred | B5: Chase | C5: Personal | D5: 95 | E5: Verify — 100K offer ended 8/6/26 | F5: 60K–100K UR | G5: 2026-08 | H5: DoC 8/8/26 | I5: 3x dining · 2x travel · UR transfers | J5: Starter transferable-points card; unlocks Chase UR | K5: Chase fee typically waived for eligible active duty (MLA) — verify. Subject to 5/24.
A6: Chase Sapphire Reserve | B6: Chase | C6: Personal | D6: 795 | E6: 100,000 UR — $6K/3mo (Elevated) | F6: 60K–100K UR | G6: 2026-08 | H6: TPG 8/2/26 | I6: Premium travel · UR transfers | J6: Premium travel: lounges, $300 credit, protections | K6: Fee typically waived for eligible active duty — verify. Subject to 5/24.
A7: American Express Gold | B7: Amex | C7: Personal | D7: 325 | E7: Up to 100,000 MR — $8K/6mo (Elevated) | F7: 60K–90K MR | G7: 2026-08 | H7: TPG 8/2/26 | I7: 4x dining · 4x U.S. supermarkets | J7: Food earning engine for MR | K7: SCRA/MLA fee waiver typical for eligible active duty — verify. Amex once-per-lifetime language.
A8: American Express Platinum | B8: Amex | C8: Personal | D8: 895 | E8: Up to 175,000 MR — $12K/6mo (Elevated) | F8: 80K–150K MR | G8: 2026-08 | H8: TPG 8/2/26 | I8: 5x flights · premium credits | J8: Premium travel benefits: lounges, credits, status | K8: SCRA/MLA waiver typical — verify. Offers vary by applicant.
A9: Amex Charles Schwab Platinum | B9: Amex | C9: Personal | D9: 895 | E9: Verify with issuer | F9: Tracks Platinum family | G9: 2026-08 | H9: — | I9: Platinum benefits + MR→Schwab cash-out | J9: MR → brokerage redemption strategy | K9: Requires Schwab account. SCRA/MLA waiver typical — verify.
A10: Capital One Venture X | B10: Capital One | C10: Personal | D10: 395 | E10: Verify — prior offers ended 4/30/26 | F10: Commonly 75K miles | G10: 2026-08 | H10: DoC 8/8/26 | I10: 2x everything · portal 10x hotels | J10: Value-premium travel with lounge access | K10: Military fee policy: verify with Capital One.
A11: Capital One Venture | B11: Capital One | C11: Personal | D11: 95 | E11: Verify with issuer | F11: Commonly 75K miles | G11: 2026-08 | H11: — | I11: 2x everything | J11: Simple flat travel earning | K11: Military fee policy: verify.
A12: Capital One Savor | B12: Capital One | C12: Personal | D12: 0 | E12: $250 — $500/3mo | F12: $200–$300 | G12: 2026-08 | H12: DoC 8/8/26 | I12: 3% dining/entertainment/groceries | J12: No-fee food & fun earner | K12: —
A13: Citi Strata Premier | B13: Citi | C13: Personal | D13: 95 | E13: Verify with issuer | F13: 60K–75K TY | G13: 2026-08 | H13: — | I13: 3x dining/groceries/gas/air/hotels | J13: Broad earning + ThankYou transfers | K13: Military fee policy varies — verify with Citi.
A14: Wells Fargo Autograph Journey | B14: Wells Fargo | C14: Personal | D14: 95 | E14: Verify with issuer | F14: 60K at launch | G14: 2026-08 | H14: CNBC | I14: 5x hotels · 4x airlines | J14: Transferable points outside big-3 | K14: Military fee policy: verify.
A15: Chase Freedom Unlimited | B15: Chase | C15: Personal | D15: 0 | E15: $200 — $500/3mo | F15: $150–$250 | G15: 2026-08 | H15: DoC 8/8/26 | I15: 1.5x everything · 3x dining | J15: No-fee catch-all; feeds UR with Sapphire | K15: Subject to 5/24.
A16: Chase Freedom Flex | B16: Chase | C16: Personal | D16: 0 | E16: Verify with issuer | F16: $200 | G16: 2026-08 | H16: — | I16: 5x rotating categories | J16: Quarterly 5x earner for UR stack | K16: Subject to 5/24.
... A34: Chase Ink Business Cash | B34: Chase | C34: Business | D34: 0 | E34: $1,000 — $8K/4mo (Elevated) | F34: $350–$750 | G34: 2026-08 | H34: TPG 8/2/26 | I34: 5% office categories | J34: No-fee business earner | K34: Business required.

Sheet MY STRATEGY
A1: THE FINAL PAGE · YOUR PERSONAL STRATEGY
A2: MY CREDIT CARD STRATEGY
A3: The one page that matters — consolidate everything you worked out above. Print it. Screenshot it. Live it.
A5: My current situation (one honest sentence) | B5: Solid income, 3 cards, bonus in progress, emergency fund at 2.4 months
A6: Total credit limits / balances / utilization (auto) | B6: =IF('3. CARD AUDIT'!C18=0,"— complete Section 3 —",TEXT('3. CARD AUDIT'!C18,"$#,##0")&" / "&TEXT('3. CARD AUDIT'!D18,"$#,##0")&" / "&TEXT('3. CARD AUDIT'!H18,"0.0%")) -> $10,000 / $850 / 8.5%
A7: Total annual fees I pay (auto, from Section 9) | B7: =IF('9. FEE ANALYSIS'!B16=0,"— complete Section 9 —",TEXT('9. FEE ANALYSIS'!B16,"$#,##0")) -> $325
A8: My primary rewards goal | B8: One great trip per year, paid mostly with points
A9: My rewards ecosystem (from Section 5 quiz) | B9: Transferable points — Chase UR + Amex MR
A10: My current cards (summary) | B10: Amex Gold · Freedom Unlimited · [oldest no-fee card]
A11: Cards I will KEEP | B11: Amex Gold (food engine), Freedom Unlimited (flat anchor), oldest card (history)
A12: Cards I will DOWNGRADE or CANCEL | B12: None right now — re-run Section 9 at each renewal
A13: My NEXT card | B13: Chase Sapphire Preferred
A14: Why — and what must happen first | B14: Unlocks UR transfers for the travel goal. First: finish the Gold bonus, utilization under 10%.
A15: My 12-month plan in one line | B15: Q1 finish bonus → Q2 apply CSP → Q3 meet spend with planned purchases → Q4 book spring trip
A16: My rules (the ones I most need to hear) | B16: Pay in full, always. No spending for points. Review fees every renewal.
A18: Signed (your name) and date — a strategy you sign is a strategy you follow:
A20: Educational planning tool — not financial advice. Approvals never guaranteed; offers and terms change without notice — verify with each issuer. Rewards only have value when balances are paid in full.
